CHANGES.rst
CONTRIBUTORS.rst
DEVELOP.rst
LICENSE.GPL
LICENSE.rst
MANIFEST.in
README.rst
setup.cfg
setup.py
docs/conf.py
docs/index.rst
src/redturtle/__init__.py
src/redturtle.chefcookie.egg-info/PKG-INFO
src/redturtle.chefcookie.egg-info/SOURCES.txt
src/redturtle.chefcookie.egg-info/dependency_links.txt
src/redturtle.chefcookie.egg-info/entry_points.txt
src/redturtle.chefcookie.egg-info/namespace_packages.txt
src/redturtle.chefcookie.egg-info/not-zip-safe
src/redturtle.chefcookie.egg-info/requires.txt
src/redturtle.chefcookie.egg-info/top_level.txt
src/redturtle/chefcookie/__init__.py
src/redturtle/chefcookie/configure.zcml
src/redturtle/chefcookie/defaults.py
src/redturtle/chefcookie/interfaces.py
src/redturtle/chefcookie/permissions.zcml
src/redturtle/chefcookie/setuphandlers.py
src/redturtle/chefcookie/testing.py
src/redturtle/chefcookie/upgrades.py
src/redturtle/chefcookie/upgrades.zcml
src/redturtle/chefcookie/browser/__init__.py
src/redturtle/chefcookie/browser/chefcookie_consent_registry.py
src/redturtle/chefcookie/browser/configure.zcml
src/redturtle/chefcookie/browser/controlpanel.py
src/redturtle/chefcookie/browser/cookie_config.py
src/redturtle/chefcookie/browser/viewlets.py
src/redturtle/chefcookie/browser/overrides/.gitkeep
src/redturtle/chefcookie/browser/static/.gitkeep
src/redturtle/chefcookie/browser/static/cookie-settings.png
src/redturtle/chefcookie/browser/static/redturtle_chefcookie.js
src/redturtle/chefcookie/browser/static/redturtle_chefcookie_tech.js
src/redturtle/chefcookie/browser/static/styles.css
src/redturtle/chefcookie/browser/static/chefcookie/.babelrc
src/redturtle/chefcookie/browser/static/chefcookie/.eslintrc.js
src/redturtle/chefcookie/browser/static/chefcookie/.gitignore
src/redturtle/chefcookie/browser/static/chefcookie/.nvmrc
src/redturtle/chefcookie/browser/static/chefcookie/.prettierrc
src/redturtle/chefcookie/browser/static/chefcookie/LICENSE
src/redturtle/chefcookie/browser/static/chefcookie/README.md
src/redturtle/chefcookie/browser/static/chefcookie/chefcookie.min.js
src/redturtle/chefcookie/browser/static/chefcookie/package.json
src/redturtle/chefcookie/browser/static/chefcookie/yarn.lock
src/redturtle/chefcookie/browser/static/chefcookie/_js/_helper.js
src/redturtle/chefcookie/browser/static/chefcookie/_js/script.js
src/redturtle/chefcookie/browser/static/chefcookie/_tests/index.html
