Metadata-Version: 2.1
Name: redturtle.chefcookie
Version: 2.0.2
Summary: Cookie policy integration with chefookie
Home-page: https://github.com/collective/redturtle.chefcookie
Author: RedTurtle
Author-email: info@redturtle.it
License: GPL version 2
Project-URL: PyPI, https://pypi.python.org/pypi/redturtle.chefcookie
Project-URL: Source, https://github.com/RedTurtle/redturtle.chefcookie
Project-URL: Tracker, https://github.com/RedTurtle/redturtle.chefcookie/issues
Keywords: Python Plone
Classifier: Development Status :: 4 - Beta
Classifier: Environment :: Web Environment
Classifier: Framework :: Plone
Classifier: Framework :: Plone :: Addon
Classifier: Framework :: Plone :: 5.2
Classifier: Programming Language :: Python
Classifier: Programming Language :: Python :: 2.7
Classifier: Programming Language :: Python :: 3.7
Classifier: Programming Language :: Python :: 3.8
Classifier: Operating System :: OS Independent
Classifier: License :: OSI Approved :: GNU General Public License v2 (GPLv2)
Requires-Python: >=2.7
Provides-Extra: test
License-File: LICENSE.GPL
License-File: LICENSE.rst
